LICENSE
MANIFEST.in
NOTICE
README.md
pyproject.toml
requirements.txt
requirements_benchmarking.txt
requirements_distributed.txt
requirements_explain.txt
requirements_extra.txt
requirements_hyperopt.txt
requirements_llm.txt
requirements_serve.txt
requirements_test.txt
requirements_tree.txt
requirements_viz.txt
setup.cfg
setup.py
ludwig/__init__.py
ludwig/api.py
ludwig/api_annotations.py
ludwig/callbacks.py
ludwig/check.py
ludwig/cli.py
ludwig/collect.py
ludwig/constants.py
ludwig/contrib.py
ludwig/error.py
ludwig/evaluate.py
ludwig/experiment.py
ludwig/export.py
ludwig/forecast.py
ludwig/globals.py
ludwig/hyperopt_cli.py
ludwig/predict.py
ludwig/preprocess.py
ludwig/progress_bar.py
ludwig/serve.py
ludwig/train.py
ludwig/types.py
ludwig/upload.py
ludwig/visualize.py
ludwig.egg-info/PKG-INFO
ludwig.egg-info/SOURCES.txt
ludwig.egg-info/dependency_links.txt
ludwig.egg-info/entry_points.txt
ludwig.egg-info/requires.txt
ludwig.egg-info/top_level.txt
ludwig/accounting/__init__.py
ludwig/accounting/used_tokens.py
ludwig/automl/__init__.py
ludwig/automl/auto_tune_config.py
ludwig/automl/automl.py
ludwig/automl/base_config.py
ludwig/automl/defaults/base_automl_config.yaml
ludwig/automl/defaults/reference_configs.yaml
ludwig/automl/defaults/combiner/concat_config.yaml
ludwig/automl/defaults/combiner/tabnet_config.yaml
ludwig/automl/defaults/combiner/transformer_config.yaml
ludwig/automl/defaults/text/bert_config.yaml
ludwig/backend/__init__.py
ludwig/backend/_ray210_compat.py
ludwig/backend/base.py
ludwig/backend/datasource.py
ludwig/backend/deepspeed.py
ludwig/backend/horovod.py
ludwig/backend/ray.py
ludwig/backend/utils/__init__.py
ludwig/backend/utils/storage.py
ludwig/benchmarking/__init__.py
ludwig/benchmarking/artifacts.py
ludwig/benchmarking/benchmark.py
ludwig/benchmarking/profiler.py
ludwig/benchmarking/profiler_callbacks.py
ludwig/benchmarking/profiler_dataclasses.py
ludwig/benchmarking/reporting.py
ludwig/benchmarking/summarize.py
ludwig/benchmarking/summary_dataclasses.py
ludwig/benchmarking/utils.py
ludwig/combiners/__init__.py
ludwig/combiners/combiners.py
ludwig/config_sampling/__init__.py
ludwig/config_sampling/explore_schema.py
