Metadata-Version: 2.1
Name: ludwig
Version: 0.10.4
Summary: Declarative machine learning: End-to-end machine learning pipelines using data-driven configurations.
Home-page: https://github.com/ludwig-ai/ludwig
Author: Piero Molino
Author-email: piero.molino@gmail.com
License: Apache 2.0
Download-URL: https://pypi.org/project/ludwig/
Keywords: ludwig deep learning deep_learning machine machine_learning natural language processing computer vision
Platform: UNKNOWN
Requires-Python: >=3.8
Provides-Extra: serve
Provides-Extra: viz
Provides-Extra: distributed
Provides-Extra: hyperopt
Provides-Extra: tree
Provides-Extra: llm
Provides-Extra: explain
Provides-Extra: benchmarking
Provides-Extra: full
Provides-Extra: test
Provides-Extra: extra
